xcodec2/__init__.py
xcodec2/configuration_bigcodec.py
xcodec2/modeling_xcodec2.py
xcodec2/module.py
xcodec2/test.py
xcodec2/vq/__init__.py
xcodec2/vq/activations.py
xcodec2/vq/blocks.py
xcodec2/vq/bs_roformer5.py
xcodec2/vq/codec_decoder.py
xcodec2/vq/codec_decoder_vocos.py
xcodec2/vq/codec_encoder.py
xcodec2/vq/factorized_vector_quantize.py
xcodec2/vq/module.py
xcodec2/vq/residual_vq.py
xcodec2/vq/unet.py
xcodec2/vq/alias_free_torch/__init__.py
xcodec2/vq/alias_free_torch/act.py
xcodec2/vq/alias_free_torch/filter.py
xcodec2/vq/alias_free_torch/resample.py
xcodec2-0.1.4.dist-info/METADATA
xcodec2-0.1.4.dist-info/WHEEL
xcodec2-0.1.4.dist-info/top_level.txt
xcodec2-0.1.4.dist-info/RECORD
