Metadata-Version: 2.1
Name: xcodec2
Version: 0.1.4
Summary: A library for XCodec2 model.
Home-page: https://huggingface.co/HKUST-Audio/xcodec2
Author: Zhen Ye
Author-email: zhenye213@gmail.com
Classifier: Programming Language :: Python :: 3
Classifier: License :: OSI Approved :: MIT License
Classifier: Operating System :: OS Independent
Requires-Python: >=3.9
Requires-Dist: accelerate>=1.1.0
Requires-Dist: aiohappyeyeballs>=2.4.0
Requires-Dist: aiohttp>=3.10.5
Requires-Dist: aiosignal>=1.3.1
Requires-Dist: annotated-types>=0.7.0
Requires-Dist: antlr4-python3-runtime>=4.9.3
Requires-Dist: async-timeout>=4.0.3
Requires-Dist: attrs>=24.2.0
Requires-Dist: audioread>=3.0.1
Requires-Dist: auraloss>=0.4.0
Requires-Dist: blobfile>=3.0.0
Requires-Dist: certifi>=2024.8.30
Requires-Dist: cffi>=1.17.1
Requires-Dist: charset-normalizer>=3.3.2
Requires-Dist: click>=8.1.7
Requires-Dist: contourpy>=1.3.0
Requires-Dist: cycler>=0.12.1
Requires-Dist: datasets>=3.0.1
Requires-Dist: decorator>=5.1.1
Requires-Dist: deepspeed>=0.15.1
Requires-Dist: dill>=0.3.8
Requires-Dist: docker-pycreds>=0.4.0
Requires-Dist: einops>=0.8.0
Requires-Dist: einx>=0.3.0
Requires-Dist: exceptiongroup>=1.2.2
Requires-Dist: filelock>=3.16.1
Requires-Dist: fire>=0.7.0
Requires-Dist: fonttools>=4.54.1
Requires-Dist: frozendict>=2.4.5
Requires-Dist: frozenlist>=1.4.1
Requires-Dist: fsspec>=2024.6.1
Requires-Dist: gin-config>=0.5.0
Requires-Dist: gitdb>=4.0.11
Requires-Dist: GitPython>=3.1.43
Requires-Dist: hjson>=3.1.0
Requires-Dist: huggingface-hub>=0.25.1
Requires-Dist: hydra-core>=1.3.2
Requires-Dist: idna>=3.10
Requires-Dist: importlib-resources>=6.4.5
Requires-Dist: iniconfig>=2.0.0
Requires-Dist: Jinja2>=3.1.4
Requires-Dist: joblib>=1.4.2
Requires-Dist: kiwisolver>=1.4.7
Requires-Dist: lazy-loader>=0.4
Requires-Dist: librosa>=0.10.2.post1
Requires-Dist: lightning-utilities>=0.11.7
Requires-Dist: llvmlite>=0.43.0
Requires-Dist: lxml>=5.3.0
Requires-Dist: MarkupSafe>=2.1.5
Requires-Dist: matplotlib>=3.9.2
Requires-Dist: meson>=1.4.0
Requires-Dist: mpmath>=1.3.0
Requires-Dist: msgpack>=1.1.0
Requires-Dist: multidict>=6.1.0
Requires-Dist: multiprocess>=0.70.16
Requires-Dist: networkx>=3.2.1
Requires-Dist: ninja>=1.11.1.1
Requires-Dist: numba>=0.60.0
Requires-Dist: numpy>=2.0.2
Requires-Dist: nvidia-cublas-cu12>=12.1.3.1
Requires-Dist: nvidia-cuda-cupti-cu12>=12.1.105
Requires-Dist: nvidia-cuda-nvrtc-cu12>=12.1.105
Requires-Dist: nvidia-cuda-runtime-cu12>=12.1.105
Requires-Dist: nvidia-cudnn-cu12>=9.1.0.70
Requires-Dist: nvidia-cufft-cu12>=11.0.2.54
Requires-Dist: nvidia-curand-cu12>=10.3.2.106
Requires-Dist: nvidia-cusolver-cu12>=11.4.5.107
Requires-Dist: nvidia-cusparse-cu12>=12.1.0.106
Requires-Dist: nvidia-ml-py>=12.560.30
Requires-Dist: nvidia-nccl-cu12>=2.20.5
Requires-Dist: nvidia-nvjitlink-cu12>=12.6.68
Requires-Dist: nvidia-nvtx-cu12>=12.1.105
Requires-Dist: omegaconf>=2.3.0
Requires-Dist: packaging>=24.1
Requires-Dist: pandas>=2.2.3
Requires-Dist: pesq>=0.0.4
Requires-Dist: pillow>=10.4.0
Requires-Dist: platformdirs>=4.3.6
Requires-Dist: pluggy>=1.5.0
Requires-Dist: pooch>=1.8.2
Requires-Dist: protobuf>=5.28.2
Requires-Dist: psutil>=6.0.0
Requires-Dist: py-cpuinfo>=9.0.0
Requires-Dist: pyarrow>=17.0.0
Requires-Dist: pycparser>=2.22
Requires-Dist: pycryptodomex>=3.21.0
Requires-Dist: pydantic>=2.9.2
Requires-Dist: pydantic-core>=2.23.4
Requires-Dist: pydub>=0.25.1
Requires-Dist: pyparsing>=3.1.4
Requires-Dist: pystoi>=0.4.1
Requires-Dist: pytest>=8.3.3
Requires-Dist: python-dateutil>=2.9.0.post0
Requires-Dist: pytorch-lightning>=2.4.0
Requires-Dist: pytz>=2024.2
Requires-Dist: PyYAML>=6.0.2
Requires-Dist: regex>=2024.9.11
Requires-Dist: requests>=2.32.3
Requires-Dist: rotary-embedding-torch>=0.8.4
Requires-Dist: safetensors>=0.4.5
Requires-Dist: scikit-learn>=1.5.2
Requires-Dist: scipy>=1.13.1
Requires-Dist: sentencepiece>=0.2.0
Requires-Dist: sentry-sdk>=2.14.0
Requires-Dist: setproctitle>=1.3.3
Requires-Dist: six>=1.16.0
Requires-Dist: smmap>=5.0.1
Requires-Dist: soundfile>=0.12.1
Requires-Dist: soxr>=0.5.0.post1
Requires-Dist: sympy>=1.13.3
Requires-Dist: termcolor>=2.5.0
Requires-Dist: threadpoolctl>=3.5.0
Requires-Dist: tiktoken>=0.8.0
Requires-Dist: tokenizers>=0.20.1
Requires-Dist: tomli>=2.0.2
Requires-Dist: torch>=2.4.1
Requires-Dist: torchao>=0.5.0
Requires-Dist: torchaudio>=2.4.1
Requires-Dist: torchmetrics>=1.4.2
Requires-Dist: torchtune>=0.3.1
Requires-Dist: tqdm>=4.66.5
Requires-Dist: transformers>=4.45.2
Requires-Dist: triton>=3.0.0
Requires-Dist: typing-extensions>=4.12.2
Requires-Dist: tzdata>=2024.2
Requires-Dist: urllib3>=2.2.3
Requires-Dist: vector-quantize-pytorch==1.17.8
Requires-Dist: wandb>=0.18.1
Requires-Dist: xxhash>=3.5.0
Requires-Dist: yarl>=1.12.1
Requires-Dist: zipp>=3.20.2
